{
  "meta": {
    "contract": "ucc",
    "version": "1.0",
    "id": "payments-worker-state-001",
    "timestamp": "2026-03-23T09:30:00Z"
  },
  "declaration": {
    "mode": "apply",
    "target": "payments-worker-service",
    "desired_state": {
      "service": "payments-worker",
      "software_state": {
        "profile_layer": "extended_operational",
        "installation_state": "Configured",
        "runtime_state": "Running",
        "health_state": "Healthy",
        "admin_state": "Enabled",
        "dependency_state": "DepsReady",
        "derived_states": [
          "Present",
          "Ready",
          "Operational",
          "DependencyReady",
          "DependencyOperational",
          "FullyOperational"
        ]
      }
    }
  }
}
